cutter_plier/__init__.py
cutter_plier/core/__init__.py
cutter_plier/core/serializer.py
cutter_plier-0.0.1a0.dist-info/LICENSE
cutter_plier-0.0.1a0.dist-info/METADATA
cutter_plier-0.0.1a0.dist-info/WHEEL
cutter_plier-0.0.1a0.dist-info/top_level.txt
cutter_plier-0.0.1a0.dist-info/RECORD
